{"type": "Feature", "id": 12523620, "geometry": {"type": "Point", "coordinates": [-70.595238, -32.835171]}, "properties": {"woe:id": 12523620, "woe:parent_id": 349923, "woe:name": "Los Andes Airport", "woe:placetype": 14, "woe:placetype_name": "Airport", "woe:lang": "ENG", "iso:country": "CL", "meta:provider": ["geoplanet:7.3.1", "geoplanet:7.3.2", "geoplanet:7.4.0", "geoplanet:7.4.1", "geoplanet:7.5.1", "geoplanet:7.5.2", "geoplanet:7.6.0", "geoplanet:7.8.1", "geoplanet:7.9.0", "geoplanet:7.10.0", "geoplanet:8.0.0", "woeplanet:8.0.0"], "meta:indexed": "2020-08-20T20:49:04.240254", "woe:alias_ENG_V": ["LOB Airport", "LOB"], "meta:updated": "2020-10-14T11:09:09.746528", "woe:hierarchy": {"continent": 24865673, "country": 23424782, "town": 0, "planet": 1, "county": 26794002, "suburb": 0, "state": 2345018, "region": 0, "localadmin": 26794326}, "woe:timezone_id": 28350790, "woe:hash": "66jv1wd178rr", "woe:centroid": [-70.595238, -32.835171], "geom:latitude": -32.835171, "geom:longitude": -70.595238, "geom:hash": "66jv1wd178rr", "woe:latitude": -32.835171, "geom:centroid": [-70.595238, -32.835171], "woe:longitude": -70.595238, "woe:repo": "woeplanet-airport-cl", "geom:area": 0.0, "woe:scale": 19}}