{"type": "Feature", "id": 12512318, "properties": {"woe:id": 12512318, "woe:parent_id": 349885, "woe:name": "El Belloto Airport", "woe:placetype": 14, "woe:placetype_name": "Airport", "woe:lang": "ENG", "iso:country": "CL", "meta:provider": ["geoplanet:7.3.1", "geoplanet:7.3.2", "geoplanet:7.4.0", "geoplanet:7.4.1", "geoplanet:7.5.1", "geoplanet:7.5.2", "geoplanet:7.6.0", "geoplanet:7.8.1", "geoplanet:7.9.0", "geoplanet:7.10.0", "geoplanet:8.0.0", "woeplanet:8.0.0"], "meta:indexed": "2020-08-20T20:49:04.214777", "meta:updated": "2020-08-22T02:58:56.217667", "woe:hierarchy": {"continent": 24865673, "country": 23424782, "town": 0, "planet": 1, "county": 26794022, "suburb": 0, "state": 2345018, "region": 0, "localadmin": 26794355}, "woe:timezone_id": 28350790, "woe:hash": "66j5zp8s5qk4", "woe:centroid": [-71.410301, -33.048901], "geom:latitude": -33.048901, "geom:longitude": -71.410301, "geom:hash": "66j5zp8s5qk4", "woe:latitude": -33.048901, "geom:centroid": [-71.410301, -33.048901], "woe:longitude": -71.410301, "woe:repo": "woeplanet-airport-cl"}, "geometry": {"coordinates": [-71.410301, -33.048901], "type": "Point"}}