{"type": "Feature", "id": 12523534, "geometry": {"type": "Point", "coordinates": [-72.714508, -42.929001]}, "properties": {"woe:id": 12523534, "woe:parent_id": 349899, "woe:name": "Chaiten Airport", "woe:placetype": 14, "woe:placetype_name": "Airport", "woe:lang": "ENG", "iso:country": "CL", "meta:provider": ["geoplanet:7.3.1", "geoplanet:7.3.2", "geoplanet:7.4.0", "geoplanet:7.4.1", "geoplanet:7.5.1", "geoplanet:7.5.2", "geoplanet:7.6.0", "geoplanet:7.8.1", "geoplanet:7.9.0", "geoplanet:7.10.0", "geoplanet:8.0.0", "woeplanet:8.0.0"], "meta:indexed": "2020-08-20T20:49:04.236669", "woe:alias_ENG_V": ["WCH Airport", "WCH"], "meta:updated": "2020-10-14T11:09:09.751353", "woe:hierarchy": {"continent": 24865673, "country": 23424782, "town": 0, "planet": 1, "county": 26794009, "suburb": 0, "state": 2345026, "region": 0, "localadmin": 26794175}, "woe:timezone_id": 28350790, "woe:hash": "62k7c34bmnjn", "woe:centroid": [-72.714508, -42.929001], "geom:latitude": -42.929001, "geom:longitude": -72.714508, "geom:hash": "62k7c34bmnjn", "woe:latitude": -42.929001, "geom:centroid": [-72.714508, -42.929001], "woe:longitude": -72.714508, "woe:repo": "woeplanet-airport-cl", "geom:area": 0.0, "woe:scale": 19}}