{"type": "Feature", "id": 12523678, "properties": {"woe:id": 12523678, "woe:parent_id": 349944, "woe:name": "Puerto Aisen Airport", "woe:placetype": 14, "woe:placetype_name": "Airport", "woe:lang": "ENG", "iso:country": "CL", "meta:provider": ["geoplanet:7.3.1", "geoplanet:7.3.2", "geoplanet:7.4.0", "geoplanet:7.4.1", "geoplanet:7.5.1", "geoplanet:7.5.2", "geoplanet:7.6.0", "geoplanet:7.8.1", "geoplanet:7.9.0", "geoplanet:7.10.0", "geoplanet:8.0.0", "woeplanet:8.0.0"], "meta:indexed": "2020-08-20T20:49:04.243075", "woe:alias_ENG_V": ["WPA Airport", "WPA", "Pto Aisen Airport"], "meta:updated": "2020-08-22T02:58:56.229090", "woe:hierarchy": {"continent": 24865673, "country": 23424782, "town": 0, "planet": 1, "county": 26793973, "suburb": 0, "state": 2345019, "region": 0, "localadmin": 26794023}, "woe:timezone_id": 28350790, "woe:hash": "4rum9sjkx3c5", "woe:centroid": [-72.699997, -45.416698], "geom:latitude": -45.416698, "geom:longitude": -72.699997, "geom:hash": "4rum9sjkx3c5", "woe:latitude": -45.416698, "geom:centroid": [-72.699997, -45.416698], "woe:longitude": -72.699997, "woe:repo": "woeplanet-airport-cl"}, "geometry": {"coordinates": [-72.699997, -45.416698], "type": "Point"}}